Crossover/__init__.py
Crossover/__version__.py
Crossover/callbacks.py
Crossover/client.py
Crossover/converters.py
Crossover/render.py
Crossover/utils.py
crossover-0.0.1.dist-info/METADATA
crossover-0.0.1.dist-info/WHEEL
crossover-0.0.1.dist-info/licenses/LICENSE
crossover-0.0.1.dist-info/RECORD
