Metadata-Version: 2.1
Name: Crossover
Version: 0.0.1
Summary: Converts Notion pages to Medium stories.
Author-email: Zhuolin Fu <fzhuolin@gmail.com>
License-File: LICENSE
Classifier: License :: OSI Approved :: MIT License
Classifier: Operating System :: OS Independent
Classifier: Programming Language :: Python :: 3
Requires-Python: >=3.8
